mitm_handle/__init__.py
mitm_handle/mitm_handle.abi3.so
mitm_handle/mitm_handle.pyi
mitm_handle-2.2.9.dist-info/METADATA
mitm_handle-2.2.9.dist-info/WHEEL
mitm_handle-2.2.9.dist-info/RECORD
