Metadata-Version: 2.4
Name: mitm_handle
Version: 2.2.9
Requires-Dist: mitmproxy
Requires-Dist: cachetools
Requires-Dist: regex
Requires-Dist: lxml
Requires-Dist: orjson
Requires-Python: >=3.12
